{"metadata": {"dbt_schema_version": "https://schemas.getdbt.com/dbt/run-results/v4.json", "dbt_version": "1.6.0", "generated_at": "2023-08-15T05:25:58.723202Z", "invocation_id": "ba6793dc-354c-4c1c-8589-e392ffe25c32", "env": {}}, "results": [{"status": "success", "timing": [{"name": "compile", "started_at": "2023-08-15T05:25:55.801830Z", "completed_at": "2023-08-15T05:25:55.810110Z"}, {"name": "execute", "started_at": "2023-08-15T05:25:55.851941Z", "completed_at": "2023-08-15T05:25:56.054633Z"}], "thread_id": "Thread-2", "execution_time": 0.26755547523498535, "adapter_response": {"_message": "OK"}, "message": "OK", "failures": null, "unique_id": "model.sports_sims.nfl_prep_team_ratings"}, {"status": "success", "timing": [{"name": "compile", "started_at": "2023-08-15T05:25:55.790348Z", "completed_at": "2023-08-15T05:25:55.805580Z"}, {"name": "execute", "started_at": "2023-08-15T05:25:55.810959Z", "completed_at": "2023-08-15T05:25:56.074101Z"}], "thread_id": "Thread-3", "execution_time": 0.2893552780151367, "adapter_response": {"_message": "OK"}, "message": "OK", "failures": null, "unique_id": "model.sports_sims.nfl_scenario_gen"}, {"status": "success", "timing": [{"name": "compile", "started_at": "2023-08-15T05:25:55.806485Z", "completed_at": "2023-08-15T05:25:55.822021Z"}, {"name": "execute", "started_at": "2023-08-15T05:25:55.878099Z", "completed_at": "2023-08-15T05:25:56.088784Z"}], "thread_id": "Thread-1", "execution_time": 0.29375481605529785, "adapter_response": {"_message": "OK"}, "message": "OK", "failures": null, "unique_id": "model.sports_sims.nfl_prep_schedule"}, {"status": "success", "timing": [{"name": "compile", "started_at": "2023-08-15T05:25:56.061827Z", "completed_at": "2023-08-15T05:25:56.065463Z"}, {"name": "execute", "started_at": "2023-08-15T05:25:56.066847Z", "completed_at": "2023-08-15T05:25:56.144020Z"}], "thread_id": "Thread-4", "execution_time": 0.14755964279174805, "adapter_response": {"_message": "OK"}, "message": "OK", "failures": null, "unique_id": "model.sports_sims.nfl_ratings"}, {"status": "success", "timing": [{"name": "compile", "started_at": "2023-08-15T05:25:56.224262Z", "completed_at": "2023-08-15T05:25:56.232022Z"}, {"name": "execute", "started_at": "2023-08-15T05:25:56.240065Z", "completed_at": "2023-08-15T05:25:56.404754Z"}], "thread_id": "Thread-3", "execution_time": 0.19008588790893555, "adapter_response": {"_message": "OK"}, "message": "OK", "failures": null, "unique_id": "model.sports_sims.nfl_teams"}, {"status": "success", "timing": [{"name": "compile", "started_at": "2023-08-15T05:25:56.219534Z", "completed_at": "2023-08-15T05:25:56.231029Z"}, {"name": "execute", "started_at": "2023-08-15T05:25:56.234724Z", "completed_at": "2023-08-15T05:25:56.419920Z"}], "thread_id": "Thread-2", "execution_time": 0.2072904109954834, "adapter_response": {"_message": "OK"}, "message": "OK", "failures": null, "unique_id": "model.sports_sims.nfl_reg_season_schedule"}, {"status": "success", "timing": [{"name": "compile", "started_at": "2023-08-15T05:25:56.227796Z", "completed_at": "2023-08-15T05:25:56.233998Z"}, {"name": "execute", "started_at": "2023-08-15T05:25:56.247159Z", "completed_at": "2023-08-15T05:25:56.439524Z"}], "thread_id": "Thread-1", "execution_time": 0.27847933769226074, "adapter_response": {"_message": "OK"}, "message": "OK", "failures": null, "unique_id": "model.sports_sims.nfl_vegas_wins"}, {"status": "success", "timing": [{"name": "compile", "started_at": "2023-08-15T05:25:56.427111Z", "completed_at": "2023-08-15T05:25:56.431007Z"}, {"name": "execute", "started_at": "2023-08-15T05:25:56.432366Z", "completed_at": "2023-08-15T05:25:56.558791Z"}], "thread_id": "Thread-4", "execution_time": 0.18729662895202637, "adapter_response": {"_message": "OK"}, "message": "OK", "failures": null, "unique_id": "model.sports_sims.nfl_schedules"}, {"status": "success", "timing": [{"name": "compile", "started_at": "2023-08-15T05:25:56.618888Z", "completed_at": "2023-08-15T05:25:56.623306Z"}, {"name": "execute", "started_at": "2023-08-15T05:25:56.624644Z", "completed_at": "2023-08-15T05:25:56.997185Z"}], "thread_id": "Thread-2", "execution_time": 0.43582892417907715, "adapter_response": {"_message": "OK"}, "message": "OK", "failures": null, "unique_id": "model.sports_sims.nfl_random_num_gen"}, {"status": "success", "timing": [{"name": "compile", "started_at": "2023-08-15T05:25:57.059715Z", "completed_at": "2023-08-15T05:25:57.066909Z"}, {"name": "execute", "started_at": "2023-08-15T05:25:57.068270Z", "completed_at": "2023-08-15T05:25:57.133486Z"}], "thread_id": "Thread-1", "execution_time": 0.1333317756652832, "adapter_response": {"_message": "OK"}, "message": "OK", "failures": null, "unique_id": "model.sports_sims.nfl_reg_season_simulator"}, {"status": "success", "timing": [{"name": "compile", "started_at": "2023-08-15T05:25:57.204552Z", "completed_at": "2023-08-15T05:25:57.215651Z"}, {"name": "execute", "started_at": "2023-08-15T05:25:57.246242Z", "completed_at": "2023-08-15T05:25:57.335761Z"}], "thread_id": "Thread-2", "execution_time": 0.14017963409423828, "adapter_response": {"_message": "OK"}, "message": "OK", "failures": null, "unique_id": "model.sports_sims.nfl_reg_season_predictions"}, {"status": "success", "timing": [{"name": "compile", "started_at": "2023-08-15T05:25:57.200554Z", "completed_at": "2023-08-15T05:25:57.209155Z"}, {"name": "execute", "started_at": "2023-08-15T05:25:57.210565Z", "completed_at": "2023-08-15T05:25:58.336069Z"}], "thread_id": "Thread-3", "execution_time": 1.2049250602722168, "adapter_response": {"_message": "OK"}, "message": "OK", "failures": null, "unique_id": "model.sports_sims.nfl_reg_season_end"}, {"status": "success", "timing": [{"name": "compile", "started_at": "2023-08-15T05:25:58.409507Z", "completed_at": "2023-08-15T05:25:58.414239Z"}, {"name": "execute", "started_at": "2023-08-15T05:25:58.415596Z", "completed_at": "2023-08-15T05:25:58.591468Z"}], "thread_id": "Thread-1", "execution_time": 0.24219512939453125, "adapter_response": {"_message": "OK"}, "message": "OK", "failures": null, "unique_id": "model.sports_sims.nfl_reg_season_summary"}], "elapsed_time": 3.065117359161377, "args": {"enable_legacy_logger": false, "introspect": true, "log_format_file": "debug", "resource_types": [], "select": ["tag:nfl"], "which": "build", "partial_parse": true, "send_anonymous_usage_stats": false, "project_dir": "/workspaces/nba-monte-carlo/transform", "defer": false, "printer_width": 80, "print": true, "vars": {}, "macro_debugging": false, "populate_cache": true, "write_json": true, "log_file_max_bytes": 10485760, "cache_selected_only": false, "indirect_selection": "eager", "version_check": true, "static_parser": true, "log_format": "default", "favor_state": false, "invocation_command": "dbt build -s tag:nfl", "quiet": false, "strict_mode": false, "use_colors_file": true, "warn_error_options": {"include": [], "exclude": []}, "log_path": "/workspaces/nba-monte-carlo/transform/logs", "show": false, "log_level_file": "debug", "use_colors": true, "log_level": "info", "exclude": [], "profiles_dir": "/workspaces/nba-monte-carlo/transform/profiles/duckdb"}}